pyocd_remote/__init__.py
pyocd_remote/__main__.py
pyocd_remote/pyocd_remote.py
pyocd_remote-0.2.2.dist-info/LICENSE.txt
pyocd_remote-0.2.2.dist-info/METADATA
pyocd_remote-0.2.2.dist-info/WHEEL
pyocd_remote-0.2.2.dist-info/entry_points.txt
pyocd_remote-0.2.2.dist-info/top_level.txt
pyocd_remote-0.2.2.dist-info/RECORD
