Metadata-Version: 2.1
Name: pyocd-remote
Version: 0.2.2
Summary: PyOCD remote execution wrapper
Home-page: https://github.com/patrislav1/pyocd_remote
Author: Patrick Huesmann
Author-email: info@patrick-huesmann.de
License: BSD
Keywords: pyocd remote jtag swd cmsis-dap
Platform: UNKNOWN
Classifier: Programming Language :: Python :: 3.6
Classifier: Operating System :: OS Independent
Classifier: Environment :: Console
Classifier: License :: OSI Approved :: BSD License
Classifier: Intended Audience :: Developers
Classifier: Development Status :: 3 - Alpha
Requires-Python: >=3.6
Requires-Dist: paramiko (>=2.7.0)
Requires-Dist: scp (>=0.13.0)
Requires-Dist: sshtunnel (>=0.3.0)
